yangsutil/__init__.py
yangsutil/datetime_util.py
yangsutil/dict_util.py
yangsutil/file_util.py
yangsutil/integer_util.py
yangsutil/log_util.py
yangsutil/object_util.py
yangsutil/printer.py
yangsutil/shield_util.py
yangsutil/string_util.py
yangsutil/web_util.py
yangsutil-0.1.0.dist-info/METADATA
yangsutil-0.1.0.dist-info/RECORD
yangsutil-0.1.0.dist-info/WHEEL
yangsutil-0.1.0.dist-info/top_level.txt
