Metadata-Version: 2.1
Name: yangsutil
Version: 0.1.0
Summary: Utilities
Home-page: https://github.com/seiren87/yangsutil
Author: seiren87
Author-email: seiren87dev@gmail.com
License: MIT
Keywords: util,datetime,request,crypt
Platform: UNKNOWN
Classifier: Intended Audience :: Developers
Classifier: Topic :: Software Development :: Libraries
Classifier: License :: OSI Approved :: MIT License
Classifier: Programming Language :: Python :: 3.5
Classifier: Programming Language :: Python :: 3.6
Requires-Python: >=3.5
Requires-Dist: dateutils (==0.6.6)
Requires-Dist: pycrypto (==2.6.1)
Requires-Dist: pyyaml (==3.12)
Requires-Dist: requests (==2.18.4)
Requires-Dist: bs4 (==0.0.1)
